<annotation>
	<folder>HelpfulCitizen4</folder>
	<filename>IMG_20200215_124239403_BURST071.jpg</filename>
	<path>C:\Users\rhollis\Pictures\HelpfulCitizen4\IMG_20200215_124239403_BURST071.jpg</path>
	<source>
		<database>Unknown</database>
	</source>
	<size>
		<width>3264</width>
		<height>1836</height>
		<depth>3</depth>
	</size>
	<segmented>0</segmented>
	<object>
		<name>energy_cell</name>
		<pose>Unspecified</pose>
		<truncated>1</truncated>
		<difficult>0</difficult>
		<bndbox>
			<xmin>1</xmin>
			<ymin>1255</ymin>
			<xmax>333</xmax>
			<ymax>1834</ymax>
		</bndbox>
	</object>
	<object>
		<name>energy_cell</name>
		<pose>Unspecified</pose>
		<truncated>0</truncated>
		<difficult>0</difficult>
		<bndbox>
			<xmin>1364</xmin>
			<ymin>302</ymin>
			<xmax>1805</xmax>
			<ymax>711</ymax>
		</bndbox>
	</object>
</annotation>
