<annotation>
	<folder>Jessica</folder>
	<filename>IMG_20200214_163902909_BURST331.jpg</filename>
	<path>C:\Users\robot\Pictures\Jessica\IMG_20200214_163902909_BURST331.jpg</path>
	<source>
		<database>Unknown</database>
	</source>
	<size>
		<width>3264</width>
		<height>1836</height>
		<depth>3</depth>
	</size>
	<segmented>0</segmented>
	<object>
		<name>energy_cell</name>
		<pose>Unspecified</pose>
		<truncated>0</truncated>
		<difficult>0</difficult>
		<bndbox>
			<xmin>2771</xmin>
			<ymin>785</ymin>
			<xmax>2925</xmax>
			<ymax>942</ymax>
		</bndbox>
	</object>
	<object>
		<name>energy_cell</name>
		<pose>Unspecified</pose>
		<truncated>0</truncated>
		<difficult>0</difficult>
		<bndbox>
			<xmin>1036</xmin>
			<ymin>869</ymin>
			<xmax>1203</xmax>
			<ymax>1064</ymax>
		</bndbox>
	</object>
	<object>
		<name>energy_cell</name>
		<pose>Unspecified</pose>
		<truncated>0</truncated>
		<difficult>0</difficult>
		<bndbox>
			<xmin>468</xmin>
			<ymin>737</ymin>
			<xmax>660</xmax>
			<ymax>917</ymax>
		</bndbox>
	</object>
	<object>
		<name>energy_cell</name>
		<pose>Unspecified</pose>
		<truncated>0</truncated>
		<difficult>0</difficult>
		<bndbox>
			<xmin>736</xmin>
			<ymin>642</ymin>
			<xmax>882</xmax>
			<ymax>766</ymax>
		</bndbox>
	</object>
	<object>
		<name>energy_cell</name>
		<pose>Unspecified</pose>
		<truncated>0</truncated>
		<difficult>0</difficult>
		<bndbox>
			<xmin>1182</xmin>
			<ymin>455</ymin>
			<xmax>1301</xmax>
			<ymax>580</ymax>
		</bndbox>
	</object>
</annotation>
