<annotation verified="yes">
	<folder>HelpfulCitizen4</folder>
	<filename>IMG_20200215_124113682_BURST014.jpg</filename>
	<path>C:\Users\rhollis\Pictures\HelpfulCitizen4\IMG_20200215_124113682_BURST014.jpg</path>
	<source>
		<database>Unknown</database>
	</source>
	<size>
		<width>3264</width>
		<height>1836</height>
		<depth>3</depth>
	</size>
	<segmented>0</segmented>
	<object>
		<name>energy_cell</name>
		<pose>Unspecified</pose>
		<truncated>1</truncated>
		<difficult>0</difficult>
		<bndbox>
			<xmin>57</xmin>
			<ymin>1183</ymin>
			<xmax>1271</xmax>
			<ymax>1836</ymax>
		</bndbox>
	</object>
	<object>
		<name>energy_cell</name>
		<pose>Unspecified</pose>
		<truncated>0</truncated>
		<difficult>0</difficult>
		<bndbox>
			<xmin>575</xmin>
			<ymin>496</ymin>
			<xmax>926</xmax>
			<ymax>834</ymax>
		</bndbox>
	</object>
	<object>
		<name>energy_cell</name>
		<pose>Unspecified</pose>
		<truncated>0</truncated>
		<difficult>0</difficult>
		<bndbox>
			<xmin>1535</xmin>
			<ymin>417</ymin>
			<xmax>1818</xmax>
			<ymax>634</ymax>
		</bndbox>
	</object>
	<object>
		<name>energy_cell</name>
		<pose>Unspecified</pose>
		<truncated>0</truncated>
		<difficult>0</difficult>
		<bndbox>
			<xmin>1811</xmin>
			<ymin>543</ymin>
			<xmax>2228</xmax>
			<ymax>915</ymax>
		</bndbox>
	</object>
	<object>
		<name>energy_cell</name>
		<pose>Unspecified</pose>
		<truncated>0</truncated>
		<difficult>0</difficult>
		<bndbox>
			<xmin>2394</xmin>
			<ymin>538</ymin>
			<xmax>2907</xmax>
			<ymax>945</ymax>
		</bndbox>
	</object>
	<object>
		<name>energy_cell</name>
		<pose>Unspecified</pose>
		<truncated>1</truncated>
		<difficult>0</difficult>
		<bndbox>
			<xmin>3026</xmin>
			<ymin>507</ymin>
			<xmax>3264</xmax>
			<ymax>856</ymax>
		</bndbox>
	</object>
</annotation>
