<annotation>
	<folder>Stickles</folder>
	<filename>IMG_20200214_161600488.jpg</filename>
	<path>/home/neobot/Desktop/Stickles/IMG_20200214_161600488.jpg</path>
	<source>
		<database>Unknown</database>
	</source>
	<size>
		<width>3264</width>
		<height>1836</height>
		<depth>3</depth>
	</size>
	<segmented>0</segmented>
	<object>
		<name>energy_cell</name>
		<pose>Unspecified</pose>
		<truncated>0</truncated>
		<difficult>0</difficult>
		<bndbox>
			<xmin>1763</xmin>
			<ymin>197</ymin>
			<xmax>1906</xmax>
			<ymax>360</ymax>
		</bndbox>
	</object>
	<object>
		<name>energy_cell</name>
		<pose>Unspecified</pose>
		<truncated>0</truncated>
		<difficult>0</difficult>
		<bndbox>
			<xmin>1625</xmin>
			<ymin>178</ymin>
			<xmax>1772</xmax>
			<ymax>332</ymax>
		</bndbox>
	</object>
	<object>
		<name>energy_cell</name>
		<pose>Unspecified</pose>
		<truncated>0</truncated>
		<difficult>0</difficult>
		<bndbox>
			<xmin>1750</xmin>
			<ymin>832</ymin>
			<xmax>1988</xmax>
			<ymax>1078</ymax>
		</bndbox>
	</object>
	<object>
		<name>energy_cell</name>
		<pose>Unspecified</pose>
		<truncated>0</truncated>
		<difficult>0</difficult>
		<bndbox>
			<xmin>903</xmin>
			<ymin>603</ymin>
			<xmax>1113</xmax>
			<ymax>810</ymax>
		</bndbox>
	</object>
	<object>
		<name>energy_cell</name>
		<pose>Unspecified</pose>
		<truncated>1</truncated>
		<difficult>0</difficult>
		<bndbox>
			<xmin>1</xmin>
			<ymin>841</ymin>
			<xmax>100</xmax>
			<ymax>1066</ymax>
		</bndbox>
	</object>
	<object>
		<name>energy_cell</name>
		<pose>Unspecified</pose>
		<truncated>0</truncated>
		<difficult>0</difficult>
		<bndbox>
			<xmin>500</xmin>
			<ymin>872</ymin>
			<xmax>766</xmax>
			<ymax>1100</ymax>
		</bndbox>
	</object>
	<object>
		<name>energy_cell</name>
		<pose>Unspecified</pose>
		<truncated>0</truncated>
		<difficult>0</difficult>
		<bndbox>
			<xmin>122</xmin>
			<ymin>1244</ymin>
			<xmax>447</xmax>
			<ymax>1535</ymax>
		</bndbox>
	</object>
</annotation>
